discoger/__init__.py
discoger/_info.py
discoger/client.py
discoger/scrap.py
discoger/utils.py
discoger-2.2.1.dist-info/LICENSE
discoger-2.2.1.dist-info/METADATA
discoger-2.2.1.dist-info/WHEEL
discoger-2.2.1.dist-info/entry_points.txt
discoger-2.2.1.dist-info/top_level.txt
discoger-2.2.1.dist-info/RECORD
