Metadata-Version: 2.1
Name: discoger
Version: 2.2.1
Summary: Get notification from Discogs
Home-page: https://github.com/beudbeud/discoger
Author: Beudbeud
Author-email: beudbeud@gmail.com
License: GNU General Public License v3 (GPLv3)
Download-URL: https://github.com/beudbeud/discoger/archive/2.2.1.tar.gz
Keywords: discogs,telegram,bot
Platform: UNKNOWN
Classifier: License :: OSI Approved :: GNU General Public License v3 (GPLv3)
Classifier: Development Status :: 5 - Production/Stable
Classifier: Programming Language :: Python :: 3
Classifier: Programming Language :: Python :: 3.7
Classifier: Programming Language :: Python :: 3.8
Classifier: Programming Language :: Python :: 3.9
Classifier: Topic :: Internet :: WWW/HTTP
Classifier: Operating System :: OS Independent
Requires-Python: >=3.7
